maypy/__init__.py
maypy/_exceptions.py
maypy/_functional.py
maypy/_maybe.py
maypy/predicates.py
maypy/py.typed
maypy-2.1.0.dist-info/METADATA
maypy-2.1.0.dist-info/WHEEL
maypy-2.1.0.dist-info/licenses/LICENSE
maypy-2.1.0.dist-info/RECORD
